skyaml/__init__.py
scikit_yaml-0.2.1.dist-info/LICENSE
scikit_yaml-0.2.1.dist-info/METADATA
scikit_yaml-0.2.1.dist-info/WHEEL
scikit_yaml-0.2.1.dist-info/top_level.txt
scikit_yaml-0.2.1.dist-info/RECORD
